fanfic_downloader/__init__.py
fanfic_downloader/config.py
fanfic_downloader/main.py
fanfic_downloader/utils.py
fanfic_downloader/commands/__init__.py
fanfic_downloader/commands/download.py
fanfic_downloader/commands/extract.py
fanfic_downloader/commands/help.py
fanfic_downloader/commands/list.py
fanfic_downloader/commands/settings.py
fanfic_downloader/commands/update.py
fanfic_downloader-0.3.3.dist-info/licenses/LICENCE
fanfic_downloader-0.3.3.dist-info/METADATA
fanfic_downloader-0.3.3.dist-info/WHEEL
fanfic_downloader-0.3.3.dist-info/entry_points.txt
fanfic_downloader-0.3.3.dist-info/top_level.txt
fanfic_downloader-0.3.3.dist-info/RECORD
