Metadata-Version: 2.4
Name: fanfic-downloader
Version: 0.3.3
Summary: Download fan fiction stories from various sites
Author-email: Munish Chandra Jha <mcj130101@gmail.com>
License: MIT
Project-URL: Homepage, https://github.com/mcj130101/fanfic_extractor
Project-URL: Bug Tracker, https://github.com/mcj130101/fanfic_extractor/issues
Keywords: fanfiction,cli,downloader,fanficfare,epub
Classifier: Programming Language :: Python :: 3
Classifier: License :: OSI Approved :: MIT License
Classifier: Operating System :: OS Independent
Classifier: Topic :: Text Processing
Classifier: Topic :: Utilities
Requires-Python: >=3.7
License-File: LICENCE
Requires-Dist: typer>=0.9.0
Requires-Dist: rich>=13.0.0
Requires-Dist: fanficfare>=4.0.0
Dynamic: license-file
